<?xml version="1.0"?>
<col:collection xmlns="http://cnx.rice.edu/collxml" xmlns:md="http://cnx.rice.edu/mdml" xmlns:col="http://cnx.rice.edu/collxml" xml:lang="en" type="Course" authors="Siyavula Uploaders">
  <metadata xmlns:md="http://cnx.rice.edu/mdml" mdml-version="0.5">
    <md:content-id>col10994</md:content-id>
    <md:title>Mathematics Grade 5</md:title>
    <md:license url="http://creativecommons.org/licenses/by/3.0/">Creative Commons Attribution License 3.0</md:license>
    <md:language>en</md:language>
    <md:uuid>19ef48a9-0ce5-430d-b3e4-2f48c15fbf06</md:uuid>
    <md:slug>mathematics-grade-5</md:slug>
  </metadata>
  <col:content>
    <col:subcollection>
      <md:title>Term 1</md:title>
      <col:content>
        <col:module document="m22878"/>
        <col:module document="m22879"/>
        <col:module document="m22880"/>
        <col:module document="m22881"/>
        <col:module document="m22882"/>
        <col:module document="m22751"/>
        <col:module document="m22752"/>
        <col:module document="m22753"/>
        <col:module document="m22754"/>
        <col:module document="m22757"/>
        <col:module document="m22758"/>
        <col:module document="m22760"/>
        <col:module document="m22766"/>
        <col:module document="m22768"/>
        <col:module document="m22769"/>
        <col:module document="m22770"/>
        <col:module document="m22771"/>
        <col:module document="m22772"/>
        <col:module document="m22821"/>
        <col:module document="m22822"/>
        <col:module document="m22826"/>
        <col:module document="m22828"/>
        <col:module document="m22831"/>
        <col:module document="m22871"/>
        <col:module document="m22872"/>
        <col:module document="m22873"/>
        <col:module document="m22874"/>
        <col:module document="m22875"/>
        <col:module document="m22876"/>
      </col:content>
    </col:subcollection>
    <col:subcollection>
      <md:title>Term 2</md:title>
      <col:content>
        <col:module document="m30815"/>
        <col:module document="m30816"/>
      </col:content>
    </col:subcollection>
    <col:subcollection>
      <md:title>Term 3</md:title>
      <col:content>
        <col:module document="m30933"/>
        <col:module document="m30939"/>
        <col:module document="m30942"/>
        <col:module document="m30946"/>
        <col:module document="m30951"/>
        <col:module document="m30968"/>
      </col:content>
    </col:subcollection>
    <col:subcollection>
      <md:title>Term 4</md:title>
      <col:content>
        <col:module document="m30966"/>
        <col:module document="m30973"/>
        <col:module document="m30976"/>
        <col:module document="m30977"/>
        <col:module document="m30978"/>
      </col:content>
    </col:subcollection>
  </col:content>
</col:collection>
